stock_scanner/__init__.py
stock_scanner/backtest/AnalysisResult.py
stock_scanner/backtest/AnalyzerInterface.py
stock_scanner/backtest/BacktestInterface.py
stock_scanner/backtest/Performance30Days.py
stock_scanner/backtest/__init__.py
stock_scanner/condition/AboveTwoSMAs.py
stock_scanner/condition/ConditionInterface.py
stock_scanner/condition/Consolidating.py
stock_scanner/condition/__init__.py
stock_scanner/condition/n_day_bullrun.py
stock_scanner/condition/n_green_days.py
stock_scanner/export/SaveTickersToFile.py
stock_scanner/export/SaveToInteractive.py
stock_scanner/export/SaveToPNG.py
stock_scanner/export/__init__.py
stock_scanner/scanner/BasicScanner.py
stock_scanner/scanner/ScannerInterface.py
stock_scanner/scanner/__init__.py
stock_scanner/stock/Stock.py
stock_scanner/stock/StockInterface.py
stock_scanner/stock/__init__.py
stock_scanner/stock_io/StockIoInterface.py
stock_scanner/stock_io/YahooIO.py
stock_scanner/stock_io/__init__.py
stock_scanner/validator/BasicValidator.py
stock_scanner/validator/ValidatorInterface.py
stock_scanner/validator/__init__.py
thumos_stock_screener-0.1.6.dist-info/METADATA
thumos_stock_screener-0.1.6.dist-info/WHEEL
thumos_stock_screener-0.1.6.dist-info/top_level.txt
thumos_stock_screener-0.1.6.dist-info/RECORD
