Metadata-Version: 2.1
Name: thumos-stock-screener
Version: 0.1.6
Summary: A Python framework for building stock scanners/screeners.
Home-page: https://github.com/jonmest/stock-scanner
Author: Jon Cavallie Mester
Author-email: joncavalliemester@protonmail.com
Project-URL: Bug Tracker, https://github.com/jonmest/stock-scanner/issues
Classifier: Programming Language :: Python :: 3
Classifier: License :: OSI Approved :: MIT License
Classifier: Operating System :: OS Independent
Requires-Python: >=3.6
Requires-Dist: auto-mix-prep (>=0.2.0)
Requires-Dist: mplfinance (>=0.12.9b1)
Requires-Dist: pandas (>=1.4.2)
Requires-Dist: plotly (>=5.8.2)
Requires-Dist: yahoo-fin (>=0.8.9.1)
Requires-Dist: yahooquery (>=2.2.15)
